{
	"meta": {
		"image": "magmar-spritesheet.png",
		"size": {"w":584,"h":549},
		"scale": "1"
	},
	"frames": {
		"magmar/magmar1.png":
		{
			"frame": {"x":0,"y":0,"w":73,"h":61},
			"rotated": false,
			"trimmed": false,
			"spriteSourceSize": {"x":0,"y":0,"w":73,"h":61},
			"sourceSize": {"w":73,"h":61}
		},
		"magmar/magmar10.png":
		{
			"frame": {"x":73,"y":0,"w":73,"h":61},
			"rotated": false,
			"trimmed": false,
			"spriteSourceSize": {"x":0,"y":0,"w":73,"h":61},
			"sourceSize": {"w":73,"h":61}
		},
		"magmar/magmar11.png":
		{
			"frame": {"x":0,"y":61,"w":73,"h":61},
			"rotated": false,
			"trimmed": false,
			"spriteSourceSize": {"x":0,"y":0,"w":73,"h":61},
			"sourceSize": {"w":73,"h":61}
		},
		"magmar/magmar12.png":
		{
			"frame": {"x":73,"y":61,"w":73,"h":61},
			"rotated": false,
			"trimmed": false,
			"spriteSourceSize": {"x":0,"y":0,"w":73,"h":61},
			"sourceSize": {"w":73,"h":61}
		},
		"magmar/magmar13.png":
		{
			"frame": {"x":146,"y":0,"w":73,"h":61},
			"rotated": false,
			"trimmed": false,
			"spriteSourceSize": {"x":0,"y":0,"w":73,"h":61},
			"sourceSize": {"w":73,"h":61}
		},
		"magmar/magmar14.png":
		{
			"frame": {"x":146,"y":61,"w":73,"h":61},
			"rotated": false,
			"trimmed": false,
			"spriteSourceSize": {"x":0,"y":0,"w":73,"h":61},
			"sourceSize": {"w":73,"h":61}
		},
		"magmar/magmar15.png":
		{
			"frame": {"x":0,"y":122,"w":73,"h":61},
			"rotated": false,
			"trimmed": false,
			"spriteSourceSize": {"x":0,"y":0,"w":73,"h":61},
			"sourceSize": {"w":73,"h":61}
		},
		"magmar/magmar16.png":
		{
			"frame": {"x":73,"y":122,"w":73,"h":61},
			"rotated": false,
			"trimmed": false,
			"spriteSourceSize": {"x":0,"y":0,"w":73,"h":61},
			"sourceSize": {"w":73,"h":61}
		},
		"magmar/magmar17.png":
		{
			"frame": {"x":146,"y":122,"w":73,"h":61},
			"rotated": false,
			"trimmed": false,
			"spriteSourceSize": {"x":0,"y":0,"w":73,"h":61},
			"sourceSize": {"w":73,"h":61}
		},
		"magmar/magmar18.png":
		{
			"frame": {"x":219,"y":0,"w":73,"h":61},
			"rotated": false,
			"trimmed": false,
			"spriteSourceSize": {"x":0,"y":0,"w":73,"h":61},
			"sourceSize": {"w":73,"h":61}
		},
		"magmar/magmar19.png":
		{
			"frame": {"x":219,"y":61,"w":73,"h":61},
			"rotated": false,
			"trimmed": false,
			"spriteSourceSize": {"x":0,"y":0,"w":73,"h":61},
			"sourceSize": {"w":73,"h":61}
		},
		"magmar/magmar2.png":
		{
			"frame": {"x":219,"y":122,"w":73,"h":61},
			"rotated": false,
			"trimmed": false,
			"spriteSourceSize": {"x":0,"y":0,"w":73,"h":61},
			"sourceSize": {"w":73,"h":61}
		},
		"magmar/magmar20.png":
		{
			"frame": {"x":0,"y":183,"w":73,"h":61},
			"rotated": false,
			"trimmed": false,
			"spriteSourceSize": {"x":0,"y":0,"w":73,"h":61},
			"sourceSize": {"w":73,"h":61}
		},
		"magmar/magmar21.png":
		{
			"frame": {"x":73,"y":183,"w":73,"h":61},
			"rotated": false,
			"trimmed": false,
			"spriteSourceSize": {"x":0,"y":0,"w":73,"h":61},
			"sourceSize": {"w":73,"h":61}
		},
		"magmar/magmar22.png":
		{
			"frame": {"x":146,"y":183,"w":73,"h":61},
			"rotated": false,
			"trimmed": false,
			"spriteSourceSize": {"x":0,"y":0,"w":73,"h":61},
			"sourceSize": {"w":73,"h":61}
		},
		"magmar/magmar23.png":
		{
			"frame": {"x":219,"y":183,"w":73,"h":61},
			"rotated": false,
			"trimmed": false,
			"spriteSourceSize": {"x":0,"y":0,"w":73,"h":61},
			"sourceSize": {"w":73,"h":61}
		},
		"magmar/magmar24.png":
		{
			"frame": {"x":292,"y":0,"w":73,"h":61},
			"rotated": false,
			"trimmed": false,
			"spriteSourceSize": {"x":0,"y":0,"w":73,"h":61},
			"sourceSize": {"w":73,"h":61}
		},
		"magmar/magmar25.png":
		{
			"frame": {"x":292,"y":61,"w":73,"h":61},
			"rotated": false,
			"trimmed": false,
			"spriteSourceSize": {"x":0,"y":0,"w":73,"h":61},
			"sourceSize": {"w":73,"h":61}
		},
		"magmar/magmar26.png":
		{
			"frame": {"x":292,"y":122,"w":73,"h":61},
			"rotated": false,
			"trimmed": false,
			"spriteSourceSize": {"x":0,"y":0,"w":73,"h":61},
			"sourceSize": {"w":73,"h":61}
		},
		"magmar/magmar27.png":
		{
			"frame": {"x":292,"y":183,"w":73,"h":61},
			"rotated": false,
			"trimmed": false,
			"spriteSourceSize": {"x":0,"y":0,"w":73,"h":61},
			"sourceSize": {"w":73,"h":61}
		},
		"magmar/magmar28.png":
		{
			"frame": {"x":0,"y":244,"w":73,"h":61},
			"rotated": false,
			"trimmed": false,
			"spriteSourceSize": {"x":0,"y":0,"w":73,"h":61},
			"sourceSize": {"w":73,"h":61}
		},
		"magmar/magmar29.png":
		{
			"frame": {"x":73,"y":244,"w":73,"h":61},
			"rotated": false,
			"trimmed": false,
			"spriteSourceSize": {"x":0,"y":0,"w":73,"h":61},
			"sourceSize": {"w":73,"h":61}
		},
		"magmar/magmar3.png":
		{
			"frame": {"x":146,"y":244,"w":73,"h":61},
			"rotated": false,
			"trimmed": false,
			"spriteSourceSize": {"x":0,"y":0,"w":73,"h":61},
			"sourceSize": {"w":73,"h":61}
		},
		"magmar/magmar30.png":
		{
			"frame": {"x":219,"y":244,"w":73,"h":61},
			"rotated": false,
			"trimmed": false,
			"spriteSourceSize": {"x":0,"y":0,"w":73,"h":61},
			"sourceSize": {"w":73,"h":61}
		},
		"magmar/magmar31.png":
		{
			"frame": {"x":292,"y":244,"w":73,"h":61},
			"rotated": false,
			"trimmed": false,
			"spriteSourceSize": {"x":0,"y":0,"w":73,"h":61},
			"sourceSize": {"w":73,"h":61}
		},
		"magmar/magmar32.png":
		{
			"frame": {"x":365,"y":0,"w":73,"h":61},
			"rotated": false,
			"trimmed": false,
			"spriteSourceSize": {"x":0,"y":0,"w":73,"h":61},
			"sourceSize": {"w":73,"h":61}
		},
		"magmar/magmar33.png":
		{
			"frame": {"x":365,"y":61,"w":73,"h":61},
			"rotated": false,
			"trimmed": false,
			"spriteSourceSize": {"x":0,"y":0,"w":73,"h":61},
			"sourceSize": {"w":73,"h":61}
		},
		"magmar/magmar34.png":
		{
			"frame": {"x":365,"y":122,"w":73,"h":61},
			"rotated": false,
			"trimmed": false,
			"spriteSourceSize": {"x":0,"y":0,"w":73,"h":61},
			"sourceSize": {"w":73,"h":61}
		},
		"magmar/magmar35.png":
		{
			"frame": {"x":365,"y":183,"w":73,"h":61},
			"rotated": false,
			"trimmed": false,
			"spriteSourceSize": {"x":0,"y":0,"w":73,"h":61},
			"sourceSize": {"w":73,"h":61}
		},
		"magmar/magmar36.png":
		{
			"frame": {"x":365,"y":244,"w":73,"h":61},
			"rotated": false,
			"trimmed": false,
			"spriteSourceSize": {"x":0,"y":0,"w":73,"h":61},
			"sourceSize": {"w":73,"h":61}
		},
		"magmar/magmar37.png":
		{
			"frame": {"x":0,"y":305,"w":73,"h":61},
			"rotated": false,
			"trimmed": false,
			"spriteSourceSize": {"x":0,"y":0,"w":73,"h":61},
			"sourceSize": {"w":73,"h":61}
		},
		"magmar/magmar38.png":
		{
			"frame": {"x":73,"y":305,"w":73,"h":61},
			"rotated": false,
			"trimmed": false,
			"spriteSourceSize": {"x":0,"y":0,"w":73,"h":61},
			"sourceSize": {"w":73,"h":61}
		},
		"magmar/magmar39.png":
		{
			"frame": {"x":146,"y":305,"w":73,"h":61},
			"rotated": false,
			"trimmed": false,
			"spriteSourceSize": {"x":0,"y":0,"w":73,"h":61},
			"sourceSize": {"w":73,"h":61}
		},
		"magmar/magmar4.png":
		{
			"frame": {"x":219,"y":305,"w":73,"h":61},
			"rotated": false,
			"trimmed": false,
			"spriteSourceSize": {"x":0,"y":0,"w":73,"h":61},
			"sourceSize": {"w":73,"h":61}
		},
		"magmar/magmar40.png":
		{
			"frame": {"x":292,"y":305,"w":73,"h":61},
			"rotated": false,
			"trimmed": false,
			"spriteSourceSize": {"x":0,"y":0,"w":73,"h":61},
			"sourceSize": {"w":73,"h":61}
		},
		"magmar/magmar41.png":
		{
			"frame": {"x":365,"y":305,"w":73,"h":61},
			"rotated": false,
			"trimmed": false,
			"spriteSourceSize": {"x":0,"y":0,"w":73,"h":61},
			"sourceSize": {"w":73,"h":61}
		},
		"magmar/magmar42.png":
		{
			"frame": {"x":0,"y":366,"w":73,"h":61},
			"rotated": false,
			"trimmed": false,
			"spriteSourceSize": {"x":0,"y":0,"w":73,"h":61},
			"sourceSize": {"w":73,"h":61}
		},
		"magmar/magmar43.png":
		{
			"frame": {"x":73,"y":366,"w":73,"h":61},
			"rotated": false,
			"trimmed": false,
			"spriteSourceSize": {"x":0,"y":0,"w":73,"h":61},
			"sourceSize": {"w":73,"h":61}
		},
		"magmar/magmar44.png":
		{
			"frame": {"x":146,"y":366,"w":73,"h":61},
			"rotated": false,
			"trimmed": false,
			"spriteSourceSize": {"x":0,"y":0,"w":73,"h":61},
			"sourceSize": {"w":73,"h":61}
		},
		"magmar/magmar45.png":
		{
			"frame": {"x":219,"y":366,"w":73,"h":61},
			"rotated": false,
			"trimmed": false,
			"spriteSourceSize": {"x":0,"y":0,"w":73,"h":61},
			"sourceSize": {"w":73,"h":61}
		},
		"magmar/magmar46.png":
		{
			"frame": {"x":292,"y":366,"w":73,"h":61},
			"rotated": false,
			"trimmed": false,
			"spriteSourceSize": {"x":0,"y":0,"w":73,"h":61},
			"sourceSize": {"w":73,"h":61}
		},
		"magmar/magmar47.png":
		{
			"frame": {"x":365,"y":366,"w":73,"h":61},
			"rotated": false,
			"trimmed": false,
			"spriteSourceSize": {"x":0,"y":0,"w":73,"h":61},
			"sourceSize": {"w":73,"h":61}
		},
		"magmar/magmar48.png":
		{
			"frame": {"x":438,"y":0,"w":73,"h":61},
			"rotated": false,
			"trimmed": false,
			"spriteSourceSize": {"x":0,"y":0,"w":73,"h":61},
			"sourceSize": {"w":73,"h":61}
		},
		"magmar/magmar49.png":
		{
			"frame": {"x":438,"y":61,"w":73,"h":61},
			"rotated": false,
			"trimmed": false,
			"spriteSourceSize": {"x":0,"y":0,"w":73,"h":61},
			"sourceSize": {"w":73,"h":61}
		},
		"magmar/magmar5.png":
		{
			"frame": {"x":438,"y":122,"w":73,"h":61},
			"rotated": false,
			"trimmed": false,
			"spriteSourceSize": {"x":0,"y":0,"w":73,"h":61},
			"sourceSize": {"w":73,"h":61}
		},
		"magmar/magmar50.png":
		{
			"frame": {"x":438,"y":183,"w":73,"h":61},
			"rotated": false,
			"trimmed": false,
			"spriteSourceSize": {"x":0,"y":0,"w":73,"h":61},
			"sourceSize": {"w":73,"h":61}
		},
		"magmar/magmar51.png":
		{
			"frame": {"x":438,"y":244,"w":73,"h":61},
			"rotated": false,
			"trimmed": false,
			"spriteSourceSize": {"x":0,"y":0,"w":73,"h":61},
			"sourceSize": {"w":73,"h":61}
		},
		"magmar/magmar52.png":
		{
			"frame": {"x":438,"y":305,"w":73,"h":61},
			"rotated": false,
			"trimmed": false,
			"spriteSourceSize": {"x":0,"y":0,"w":73,"h":61},
			"sourceSize": {"w":73,"h":61}
		},
		"magmar/magmar53.png":
		{
			"frame": {"x":438,"y":366,"w":73,"h":61},
			"rotated": false,
			"trimmed": false,
			"spriteSourceSize": {"x":0,"y":0,"w":73,"h":61},
			"sourceSize": {"w":73,"h":61}
		},
		"magmar/magmar54.png":
		{
			"frame": {"x":0,"y":427,"w":73,"h":61},
			"rotated": false,
			"trimmed": false,
			"spriteSourceSize": {"x":0,"y":0,"w":73,"h":61},
			"sourceSize": {"w":73,"h":61}
		},
		"magmar/magmar55.png":
		{
			"frame": {"x":73,"y":427,"w":73,"h":61},
			"rotated": false,
			"trimmed": false,
			"spriteSourceSize": {"x":0,"y":0,"w":73,"h":61},
			"sourceSize": {"w":73,"h":61}
		},
		"magmar/magmar56.png":
		{
			"frame": {"x":146,"y":427,"w":73,"h":61},
			"rotated": false,
			"trimmed": false,
			"spriteSourceSize": {"x":0,"y":0,"w":73,"h":61},
			"sourceSize": {"w":73,"h":61}
		},
		"magmar/magmar57.png":
		{
			"frame": {"x":219,"y":427,"w":73,"h":61},
			"rotated": false,
			"trimmed": false,
			"spriteSourceSize": {"x":0,"y":0,"w":73,"h":61},
			"sourceSize": {"w":73,"h":61}
		},
		"magmar/magmar58.png":
		{
			"frame": {"x":292,"y":427,"w":73,"h":61},
			"rotated": false,
			"trimmed": false,
			"spriteSourceSize": {"x":0,"y":0,"w":73,"h":61},
			"sourceSize": {"w":73,"h":61}
		},
		"magmar/magmar59.png":
		{
			"frame": {"x":365,"y":427,"w":73,"h":61},
			"rotated": false,
			"trimmed": false,
			"spriteSourceSize": {"x":0,"y":0,"w":73,"h":61},
			"sourceSize": {"w":73,"h":61}
		},
		"magmar/magmar6.png":
		{
			"frame": {"x":438,"y":427,"w":73,"h":61},
			"rotated": false,
			"trimmed": false,
			"spriteSourceSize": {"x":0,"y":0,"w":73,"h":61},
			"sourceSize": {"w":73,"h":61}
		},
		"magmar/magmar60.png":
		{
			"frame": {"x":511,"y":0,"w":73,"h":61},
			"rotated": false,
			"trimmed": false,
			"spriteSourceSize": {"x":0,"y":0,"w":73,"h":61},
			"sourceSize": {"w":73,"h":61}
		},
		"magmar/magmar61.png":
		{
			"frame": {"x":511,"y":61,"w":73,"h":61},
			"rotated": false,
			"trimmed": false,
			"spriteSourceSize": {"x":0,"y":0,"w":73,"h":61},
			"sourceSize": {"w":73,"h":61}
		},
		"magmar/magmar62.png":
		{
			"frame": {"x":511,"y":122,"w":73,"h":61},
			"rotated": false,
			"trimmed": false,
			"spriteSourceSize": {"x":0,"y":0,"w":73,"h":61},
			"sourceSize": {"w":73,"h":61}
		},
		"magmar/magmar63.png":
		{
			"frame": {"x":511,"y":183,"w":73,"h":61},
			"rotated": false,
			"trimmed": false,
			"spriteSourceSize": {"x":0,"y":0,"w":73,"h":61},
			"sourceSize": {"w":73,"h":61}
		},
		"magmar/magmar64.png":
		{
			"frame": {"x":511,"y":244,"w":73,"h":61},
			"rotated": false,
			"trimmed": false,
			"spriteSourceSize": {"x":0,"y":0,"w":73,"h":61},
			"sourceSize": {"w":73,"h":61}
		},
		"magmar/magmar65.png":
		{
			"frame": {"x":511,"y":305,"w":73,"h":61},
			"rotated": false,
			"trimmed": false,
			"spriteSourceSize": {"x":0,"y":0,"w":73,"h":61},
			"sourceSize": {"w":73,"h":61}
		},
		"magmar/magmar7.png":
		{
			"frame": {"x":511,"y":366,"w":73,"h":61},
			"rotated": false,
			"trimmed": false,
			"spriteSourceSize": {"x":0,"y":0,"w":73,"h":61},
			"sourceSize": {"w":73,"h":61}
		},
		"magmar/magmar8.png":
		{
			"frame": {"x":511,"y":427,"w":73,"h":61},
			"rotated": false,
			"trimmed": false,
			"spriteSourceSize": {"x":0,"y":0,"w":73,"h":61},
			"sourceSize": {"w":73,"h":61}
		},
		"magmar/magmar9.png":
		{
			"frame": {"x":0,"y":488,"w":73,"h":61},
			"rotated": false,
			"trimmed": false,
			"spriteSourceSize": {"x":0,"y":0,"w":73,"h":61},
			"sourceSize": {"w":73,"h":61}
		}
	}
}