{
	"meta": {
		"image": "parasect-spritesheet.png",
		"size": {"w":558,"h":504},
		"scale": "1"
	},
	"frames": {
		"parasect/parasect1.png":
		{
			"frame": {"x":0,"y":0,"w":62,"h":63},
			"rotated": false,
			"trimmed": false,
			"spriteSourceSize": {"x":0,"y":0,"w":62,"h":63},
			"sourceSize": {"w":62,"h":63}
		},
		"parasect/parasect10.png":
		{
			"frame": {"x":62,"y":0,"w":62,"h":63},
			"rotated": false,
			"trimmed": false,
			"spriteSourceSize": {"x":0,"y":0,"w":62,"h":63},
			"sourceSize": {"w":62,"h":63}
		},
		"parasect/parasect11.png":
		{
			"frame": {"x":124,"y":0,"w":62,"h":63},
			"rotated": false,
			"trimmed": false,
			"spriteSourceSize": {"x":0,"y":0,"w":62,"h":63},
			"sourceSize": {"w":62,"h":63}
		},
		"parasect/parasect12.png":
		{
			"frame": {"x":0,"y":63,"w":62,"h":63},
			"rotated": false,
			"trimmed": false,
			"spriteSourceSize": {"x":0,"y":0,"w":62,"h":63},
			"sourceSize": {"w":62,"h":63}
		},
		"parasect/parasect13.png":
		{
			"frame": {"x":62,"y":63,"w":62,"h":63},
			"rotated": false,
			"trimmed": false,
			"spriteSourceSize": {"x":0,"y":0,"w":62,"h":63},
			"sourceSize": {"w":62,"h":63}
		},
		"parasect/parasect14.png":
		{
			"frame": {"x":124,"y":63,"w":62,"h":63},
			"rotated": false,
			"trimmed": false,
			"spriteSourceSize": {"x":0,"y":0,"w":62,"h":63},
			"sourceSize": {"w":62,"h":63}
		},
		"parasect/parasect15.png":
		{
			"frame": {"x":186,"y":0,"w":62,"h":63},
			"rotated": false,
			"trimmed": false,
			"spriteSourceSize": {"x":0,"y":0,"w":62,"h":63},
			"sourceSize": {"w":62,"h":63}
		},
		"parasect/parasect16.png":
		{
			"frame": {"x":186,"y":63,"w":62,"h":63},
			"rotated": false,
			"trimmed": false,
			"spriteSourceSize": {"x":0,"y":0,"w":62,"h":63},
			"sourceSize": {"w":62,"h":63}
		},
		"parasect/parasect17.png":
		{
			"frame": {"x":0,"y":126,"w":62,"h":63},
			"rotated": false,
			"trimmed": false,
			"spriteSourceSize": {"x":0,"y":0,"w":62,"h":63},
			"sourceSize": {"w":62,"h":63}
		},
		"parasect/parasect18.png":
		{
			"frame": {"x":62,"y":126,"w":62,"h":63},
			"rotated": false,
			"trimmed": false,
			"spriteSourceSize": {"x":0,"y":0,"w":62,"h":63},
			"sourceSize": {"w":62,"h":63}
		},
		"parasect/parasect19.png":
		{
			"frame": {"x":124,"y":126,"w":62,"h":63},
			"rotated": false,
			"trimmed": false,
			"spriteSourceSize": {"x":0,"y":0,"w":62,"h":63},
			"sourceSize": {"w":62,"h":63}
		},
		"parasect/parasect2.png":
		{
			"frame": {"x":186,"y":126,"w":62,"h":63},
			"rotated": false,
			"trimmed": false,
			"spriteSourceSize": {"x":0,"y":0,"w":62,"h":63},
			"sourceSize": {"w":62,"h":63}
		},
		"parasect/parasect20.png":
		{
			"frame": {"x":248,"y":0,"w":62,"h":63},
			"rotated": false,
			"trimmed": false,
			"spriteSourceSize": {"x":0,"y":0,"w":62,"h":63},
			"sourceSize": {"w":62,"h":63}
		},
		"parasect/parasect21.png":
		{
			"frame": {"x":248,"y":63,"w":62,"h":63},
			"rotated": false,
			"trimmed": false,
			"spriteSourceSize": {"x":0,"y":0,"w":62,"h":63},
			"sourceSize": {"w":62,"h":63}
		},
		"parasect/parasect22.png":
		{
			"frame": {"x":248,"y":126,"w":62,"h":63},
			"rotated": false,
			"trimmed": false,
			"spriteSourceSize": {"x":0,"y":0,"w":62,"h":63},
			"sourceSize": {"w":62,"h":63}
		},
		"parasect/parasect23.png":
		{
			"frame": {"x":0,"y":189,"w":62,"h":63},
			"rotated": false,
			"trimmed": false,
			"spriteSourceSize": {"x":0,"y":0,"w":62,"h":63},
			"sourceSize": {"w":62,"h":63}
		},
		"parasect/parasect24.png":
		{
			"frame": {"x":62,"y":189,"w":62,"h":63},
			"rotated": false,
			"trimmed": false,
			"spriteSourceSize": {"x":0,"y":0,"w":62,"h":63},
			"sourceSize": {"w":62,"h":63}
		},
		"parasect/parasect25.png":
		{
			"frame": {"x":124,"y":189,"w":62,"h":63},
			"rotated": false,
			"trimmed": false,
			"spriteSourceSize": {"x":0,"y":0,"w":62,"h":63},
			"sourceSize": {"w":62,"h":63}
		},
		"parasect/parasect26.png":
		{
			"frame": {"x":186,"y":189,"w":62,"h":63},
			"rotated": false,
			"trimmed": false,
			"spriteSourceSize": {"x":0,"y":0,"w":62,"h":63},
			"sourceSize": {"w":62,"h":63}
		},
		"parasect/parasect27.png":
		{
			"frame": {"x":248,"y":189,"w":62,"h":63},
			"rotated": false,
			"trimmed": false,
			"spriteSourceSize": {"x":0,"y":0,"w":62,"h":63},
			"sourceSize": {"w":62,"h":63}
		},
		"parasect/parasect28.png":
		{
			"frame": {"x":310,"y":0,"w":62,"h":63},
			"rotated": false,
			"trimmed": false,
			"spriteSourceSize": {"x":0,"y":0,"w":62,"h":63},
			"sourceSize": {"w":62,"h":63}
		},
		"parasect/parasect29.png":
		{
			"frame": {"x":310,"y":63,"w":62,"h":63},
			"rotated": false,
			"trimmed": false,
			"spriteSourceSize": {"x":0,"y":0,"w":62,"h":63},
			"sourceSize": {"w":62,"h":63}
		},
		"parasect/parasect3.png":
		{
			"frame": {"x":310,"y":126,"w":62,"h":63},
			"rotated": false,
			"trimmed": false,
			"spriteSourceSize": {"x":0,"y":0,"w":62,"h":63},
			"sourceSize": {"w":62,"h":63}
		},
		"parasect/parasect30.png":
		{
			"frame": {"x":310,"y":189,"w":62,"h":63},
			"rotated": false,
			"trimmed": false,
			"spriteSourceSize": {"x":0,"y":0,"w":62,"h":63},
			"sourceSize": {"w":62,"h":63}
		},
		"parasect/parasect31.png":
		{
			"frame": {"x":0,"y":252,"w":62,"h":63},
			"rotated": false,
			"trimmed": false,
			"spriteSourceSize": {"x":0,"y":0,"w":62,"h":63},
			"sourceSize": {"w":62,"h":63}
		},
		"parasect/parasect32.png":
		{
			"frame": {"x":62,"y":252,"w":62,"h":63},
			"rotated": false,
			"trimmed": false,
			"spriteSourceSize": {"x":0,"y":0,"w":62,"h":63},
			"sourceSize": {"w":62,"h":63}
		},
		"parasect/parasect33.png":
		{
			"frame": {"x":124,"y":252,"w":62,"h":63},
			"rotated": false,
			"trimmed": false,
			"spriteSourceSize": {"x":0,"y":0,"w":62,"h":63},
			"sourceSize": {"w":62,"h":63}
		},
		"parasect/parasect34.png":
		{
			"frame": {"x":186,"y":252,"w":62,"h":63},
			"rotated": false,
			"trimmed": false,
			"spriteSourceSize": {"x":0,"y":0,"w":62,"h":63},
			"sourceSize": {"w":62,"h":63}
		},
		"parasect/parasect35.png":
		{
			"frame": {"x":248,"y":252,"w":62,"h":63},
			"rotated": false,
			"trimmed": false,
			"spriteSourceSize": {"x":0,"y":0,"w":62,"h":63},
			"sourceSize": {"w":62,"h":63}
		},
		"parasect/parasect36.png":
		{
			"frame": {"x":310,"y":252,"w":62,"h":63},
			"rotated": false,
			"trimmed": false,
			"spriteSourceSize": {"x":0,"y":0,"w":62,"h":63},
			"sourceSize": {"w":62,"h":63}
		},
		"parasect/parasect37.png":
		{
			"frame": {"x":372,"y":0,"w":62,"h":63},
			"rotated": false,
			"trimmed": false,
			"spriteSourceSize": {"x":0,"y":0,"w":62,"h":63},
			"sourceSize": {"w":62,"h":63}
		},
		"parasect/parasect38.png":
		{
			"frame": {"x":372,"y":63,"w":62,"h":63},
			"rotated": false,
			"trimmed": false,
			"spriteSourceSize": {"x":0,"y":0,"w":62,"h":63},
			"sourceSize": {"w":62,"h":63}
		},
		"parasect/parasect39.png":
		{
			"frame": {"x":372,"y":126,"w":62,"h":63},
			"rotated": false,
			"trimmed": false,
			"spriteSourceSize": {"x":0,"y":0,"w":62,"h":63},
			"sourceSize": {"w":62,"h":63}
		},
		"parasect/parasect4.png":
		{
			"frame": {"x":372,"y":189,"w":62,"h":63},
			"rotated": false,
			"trimmed": false,
			"spriteSourceSize": {"x":0,"y":0,"w":62,"h":63},
			"sourceSize": {"w":62,"h":63}
		},
		"parasect/parasect40.png":
		{
			"frame": {"x":372,"y":252,"w":62,"h":63},
			"rotated": false,
			"trimmed": false,
			"spriteSourceSize": {"x":0,"y":0,"w":62,"h":63},
			"sourceSize": {"w":62,"h":63}
		},
		"parasect/parasect41.png":
		{
			"frame": {"x":0,"y":315,"w":62,"h":63},
			"rotated": false,
			"trimmed": false,
			"spriteSourceSize": {"x":0,"y":0,"w":62,"h":63},
			"sourceSize": {"w":62,"h":63}
		},
		"parasect/parasect42.png":
		{
			"frame": {"x":62,"y":315,"w":62,"h":63},
			"rotated": false,
			"trimmed": false,
			"spriteSourceSize": {"x":0,"y":0,"w":62,"h":63},
			"sourceSize": {"w":62,"h":63}
		},
		"parasect/parasect43.png":
		{
			"frame": {"x":124,"y":315,"w":62,"h":63},
			"rotated": false,
			"trimmed": false,
			"spriteSourceSize": {"x":0,"y":0,"w":62,"h":63},
			"sourceSize": {"w":62,"h":63}
		},
		"parasect/parasect44.png":
		{
			"frame": {"x":186,"y":315,"w":62,"h":63},
			"rotated": false,
			"trimmed": false,
			"spriteSourceSize": {"x":0,"y":0,"w":62,"h":63},
			"sourceSize": {"w":62,"h":63}
		},
		"parasect/parasect45.png":
		{
			"frame": {"x":248,"y":315,"w":62,"h":63},
			"rotated": false,
			"trimmed": false,
			"spriteSourceSize": {"x":0,"y":0,"w":62,"h":63},
			"sourceSize": {"w":62,"h":63}
		},
		"parasect/parasect46.png":
		{
			"frame": {"x":310,"y":315,"w":62,"h":63},
			"rotated": false,
			"trimmed": false,
			"spriteSourceSize": {"x":0,"y":0,"w":62,"h":63},
			"sourceSize": {"w":62,"h":63}
		},
		"parasect/parasect47.png":
		{
			"frame": {"x":372,"y":315,"w":62,"h":63},
			"rotated": false,
			"trimmed": false,
			"spriteSourceSize": {"x":0,"y":0,"w":62,"h":63},
			"sourceSize": {"w":62,"h":63}
		},
		"parasect/parasect48.png":
		{
			"frame": {"x":434,"y":0,"w":62,"h":63},
			"rotated": false,
			"trimmed": false,
			"spriteSourceSize": {"x":0,"y":0,"w":62,"h":63},
			"sourceSize": {"w":62,"h":63}
		},
		"parasect/parasect49.png":
		{
			"frame": {"x":434,"y":63,"w":62,"h":63},
			"rotated": false,
			"trimmed": false,
			"spriteSourceSize": {"x":0,"y":0,"w":62,"h":63},
			"sourceSize": {"w":62,"h":63}
		},
		"parasect/parasect5.png":
		{
			"frame": {"x":434,"y":126,"w":62,"h":63},
			"rotated": false,
			"trimmed": false,
			"spriteSourceSize": {"x":0,"y":0,"w":62,"h":63},
			"sourceSize": {"w":62,"h":63}
		},
		"parasect/parasect50.png":
		{
			"frame": {"x":434,"y":189,"w":62,"h":63},
			"rotated": false,
			"trimmed": false,
			"spriteSourceSize": {"x":0,"y":0,"w":62,"h":63},
			"sourceSize": {"w":62,"h":63}
		},
		"parasect/parasect51.png":
		{
			"frame": {"x":434,"y":252,"w":62,"h":63},
			"rotated": false,
			"trimmed": false,
			"spriteSourceSize": {"x":0,"y":0,"w":62,"h":63},
			"sourceSize": {"w":62,"h":63}
		},
		"parasect/parasect52.png":
		{
			"frame": {"x":434,"y":315,"w":62,"h":63},
			"rotated": false,
			"trimmed": false,
			"spriteSourceSize": {"x":0,"y":0,"w":62,"h":63},
			"sourceSize": {"w":62,"h":63}
		},
		"parasect/parasect53.png":
		{
			"frame": {"x":0,"y":378,"w":62,"h":63},
			"rotated": false,
			"trimmed": false,
			"spriteSourceSize": {"x":0,"y":0,"w":62,"h":63},
			"sourceSize": {"w":62,"h":63}
		},
		"parasect/parasect54.png":
		{
			"frame": {"x":62,"y":378,"w":62,"h":63},
			"rotated": false,
			"trimmed": false,
			"spriteSourceSize": {"x":0,"y":0,"w":62,"h":63},
			"sourceSize": {"w":62,"h":63}
		},
		"parasect/parasect55.png":
		{
			"frame": {"x":124,"y":378,"w":62,"h":63},
			"rotated": false,
			"trimmed": false,
			"spriteSourceSize": {"x":0,"y":0,"w":62,"h":63},
			"sourceSize": {"w":62,"h":63}
		},
		"parasect/parasect56.png":
		{
			"frame": {"x":186,"y":378,"w":62,"h":63},
			"rotated": false,
			"trimmed": false,
			"spriteSourceSize": {"x":0,"y":0,"w":62,"h":63},
			"sourceSize": {"w":62,"h":63}
		},
		"parasect/parasect57.png":
		{
			"frame": {"x":248,"y":378,"w":62,"h":63},
			"rotated": false,
			"trimmed": false,
			"spriteSourceSize": {"x":0,"y":0,"w":62,"h":63},
			"sourceSize": {"w":62,"h":63}
		},
		"parasect/parasect58.png":
		{
			"frame": {"x":310,"y":378,"w":62,"h":63},
			"rotated": false,
			"trimmed": false,
			"spriteSourceSize": {"x":0,"y":0,"w":62,"h":63},
			"sourceSize": {"w":62,"h":63}
		},
		"parasect/parasect59.png":
		{
			"frame": {"x":372,"y":378,"w":62,"h":63},
			"rotated": false,
			"trimmed": false,
			"spriteSourceSize": {"x":0,"y":0,"w":62,"h":63},
			"sourceSize": {"w":62,"h":63}
		},
		"parasect/parasect6.png":
		{
			"frame": {"x":434,"y":378,"w":62,"h":63},
			"rotated": false,
			"trimmed": false,
			"spriteSourceSize": {"x":0,"y":0,"w":62,"h":63},
			"sourceSize": {"w":62,"h":63}
		},
		"parasect/parasect60.png":
		{
			"frame": {"x":496,"y":0,"w":62,"h":63},
			"rotated": false,
			"trimmed": false,
			"spriteSourceSize": {"x":0,"y":0,"w":62,"h":63},
			"sourceSize": {"w":62,"h":63}
		},
		"parasect/parasect61.png":
		{
			"frame": {"x":496,"y":63,"w":62,"h":63},
			"rotated": false,
			"trimmed": false,
			"spriteSourceSize": {"x":0,"y":0,"w":62,"h":63},
			"sourceSize": {"w":62,"h":63}
		},
		"parasect/parasect62.png":
		{
			"frame": {"x":496,"y":126,"w":62,"h":63},
			"rotated": false,
			"trimmed": false,
			"spriteSourceSize": {"x":0,"y":0,"w":62,"h":63},
			"sourceSize": {"w":62,"h":63}
		},
		"parasect/parasect63.png":
		{
			"frame": {"x":496,"y":189,"w":62,"h":63},
			"rotated": false,
			"trimmed": false,
			"spriteSourceSize": {"x":0,"y":0,"w":62,"h":63},
			"sourceSize": {"w":62,"h":63}
		},
		"parasect/parasect64.png":
		{
			"frame": {"x":496,"y":252,"w":62,"h":63},
			"rotated": false,
			"trimmed": false,
			"spriteSourceSize": {"x":0,"y":0,"w":62,"h":63},
			"sourceSize": {"w":62,"h":63}
		},
		"parasect/parasect65.png":
		{
			"frame": {"x":496,"y":315,"w":62,"h":63},
			"rotated": false,
			"trimmed": false,
			"spriteSourceSize": {"x":0,"y":0,"w":62,"h":63},
			"sourceSize": {"w":62,"h":63}
		},
		"parasect/parasect66.png":
		{
			"frame": {"x":496,"y":378,"w":62,"h":63},
			"rotated": false,
			"trimmed": false,
			"spriteSourceSize": {"x":0,"y":0,"w":62,"h":63},
			"sourceSize": {"w":62,"h":63}
		},
		"parasect/parasect67.png":
		{
			"frame": {"x":0,"y":441,"w":62,"h":63},
			"rotated": false,
			"trimmed": false,
			"spriteSourceSize": {"x":0,"y":0,"w":62,"h":63},
			"sourceSize": {"w":62,"h":63}
		},
		"parasect/parasect68.png":
		{
			"frame": {"x":62,"y":441,"w":62,"h":63},
			"rotated": false,
			"trimmed": false,
			"spriteSourceSize": {"x":0,"y":0,"w":62,"h":63},
			"sourceSize": {"w":62,"h":63}
		},
		"parasect/parasect69.png":
		{
			"frame": {"x":124,"y":441,"w":62,"h":63},
			"rotated": false,
			"trimmed": false,
			"spriteSourceSize": {"x":0,"y":0,"w":62,"h":63},
			"sourceSize": {"w":62,"h":63}
		},
		"parasect/parasect7.png":
		{
			"frame": {"x":186,"y":441,"w":62,"h":63},
			"rotated": false,
			"trimmed": false,
			"spriteSourceSize": {"x":0,"y":0,"w":62,"h":63},
			"sourceSize": {"w":62,"h":63}
		},
		"parasect/parasect70.png":
		{
			"frame": {"x":248,"y":441,"w":62,"h":63},
			"rotated": false,
			"trimmed": false,
			"spriteSourceSize": {"x":0,"y":0,"w":62,"h":63},
			"sourceSize": {"w":62,"h":63}
		},
		"parasect/parasect71.png":
		{
			"frame": {"x":310,"y":441,"w":62,"h":63},
			"rotated": false,
			"trimmed": false,
			"spriteSourceSize": {"x":0,"y":0,"w":62,"h":63},
			"sourceSize": {"w":62,"h":63}
		},
		"parasect/parasect8.png":
		{
			"frame": {"x":372,"y":441,"w":62,"h":63},
			"rotated": false,
			"trimmed": false,
			"spriteSourceSize": {"x":0,"y":0,"w":62,"h":63},
			"sourceSize": {"w":62,"h":63}
		},
		"parasect/parasect9.png":
		{
			"frame": {"x":434,"y":441,"w":62,"h":63},
			"rotated": false,
			"trimmed": false,
			"spriteSourceSize": {"x":0,"y":0,"w":62,"h":63},
			"sourceSize": {"w":62,"h":63}
		}
	}
}